openAIInsight/Document_TrainingPrediction.py
openAIInsight/Extract_OCR.py
openAIInsight/Image_TrainingPrediction.py
openAIInsight/Insight.py
openAIInsight/Insight_GeminiAi.py
openAIInsight/Insight_LocalAI.py
openAIInsight/Insight_OpenAI.py
openAIInsight/InvokeIntent.py
openAIInsight/InvokeIntent_Gemini.py
openAIInsight/InvokeIntent_LocalAI.py
openAIInsight/InvokeIntent_OpenAI.py
openAIInsight/OpenAI_PineConeVector.py
openAIInsight/Text_TrainingPrediction.py
openAIInsight/Weaviate.py
openAIInsight/__init__.py
openaiinsight-0.0.113.dist-info/LICENCE.txt
openaiinsight-0.0.113.dist-info/METADATA
openaiinsight-0.0.113.dist-info/WHEEL
openaiinsight-0.0.113.dist-info/top_level.txt
openaiinsight-0.0.113.dist-info/RECORD
